hexamind/__init__.py
hexamind/cli.py
hexamind/database/__init__.py
hexamind/database/adapters/AbstractDb.py
hexamind/database/adapters/ChromaDbAdapter.py
hexamind/database/adapters/DbAdapterFactory.py
hexamind/database/adapters/ElasticSearchAdapter.py
hexamind/database/adapters/QdrantAdapter.py
hexamind/database/adapters/__init__.py
hexamind/database/ingestion/__init__.py
hexamind/database/ingestion/ingestor.py
hexamind/initializer/__init__.py
hexamind/initializer/initializer.py
hexamind/llm/__init__.py
hexamind/llm/adapters/AbstractLlm.py
hexamind/llm/adapters/ChatMessageFactory.py
hexamind/llm/adapters/LlmAdapterFactory.py
hexamind/llm/adapters/__init__.py
hexamind/llm/adapters/api/MistralApiAdapter.py
hexamind/llm/adapters/api/OpenAiApiAdapter.py
hexamind/llm/adapters/api/__init__.py
hexamind/llm/adapters/op/LlmOpAdapter.py
hexamind/llm/adapters/op/__init__.py
hexamind/llm/llm/LlmAgent.py
hexamind/llm/llm/__init__.py
hexamind/model/__init__.py
hexamind/model/document.py
hexamind/model/builder/MkBuilder.py
hexamind/model/builder/__init__.py
hexamind/model/chunk/__init__.py
hexamind/model/chunk/chunk.py
hexamind/model/chunk/chunk_extractor.py
hexamind/model/chunk/itokenizer.py
hexamind/model/chunk/tokenizer.py
hexamind/model/model/__init__.py
hexamind/model/model/block.py
hexamind/model/model/container.py
hexamind/model/model/element.py
hexamind/model/readers/HtmlReader.py
hexamind/model/readers/IReader.py
hexamind/model/readers/MarkdownReader.py
hexamind/model/readers/WordReader.py
hexamind/model/readers/__init__.py
hexamind/model/summarizer/Summarizer.py
hexamind/model/summarizer/__init__.py
hexamind/retriever/__init__.py
hexamind/retriever/retriever.py
hexamind/utils/__init__.py
hexamind/utils/config/ingestor.py
hexamind/utils/config/retriever.py
hexamind/utils/llm/__init__.py
hexamind/utils/llm/template.py
hexamind/utils/llm/chat_message/__init__.py
hexamind/utils/llm/chat_message/chat_messages.py
hexamind/utils/utils/__init__.py
hexamind-0.6.2.dist-info/LICENSE
hexamind-0.6.2.dist-info/METADATA
hexamind-0.6.2.dist-info/WHEEL
hexamind-0.6.2.dist-info/entry_points.txt
hexamind-0.6.2.dist-info/top_level.txt
hexamind-0.6.2.dist-info/RECORD
