Metadata-Version: 2.1
Name: hexamind
Version: 0.6.2
Summary: Hexamind library to implement RAG solutions
Author-email: Julien Fresnel <julien.fresnel@hexamind.ai>, Max Beales <max.beales@hexamind.ai>, Alexandre Fleutelot <alexandre.fleutelot@hexamind.ai>, Quentin Fever <quentin.fever@hexamind.ai>, Louis Mucha <louis.mucha@hexamind.ai>, Yves Peligry <yves.peligry@hexamind.ai>
Requires-Python: >=3.10
License-File: LICENSE
Requires-Dist: beautifulsoup4==4.12.3
Requires-Dist: chromadb==0.5.0
Requires-Dist: elasticsearch==8.12.1
Requires-Dist: graphviz==0.20.3
Requires-Dist: mammoth==1.8.0
Requires-Dist: mistralai==0.4.1
Requires-Dist: mistral-common==1.3.4
Requires-Dist: openai==1.34.0
Requires-Dist: pytest==8.2.2
Requires-Dist: python-docx==1.1.0
Requires-Dist: Requests==2.32.3
Requires-Dist: Markdown==3.6
Requires-Dist: setuptools==68.2.2
Requires-Dist: pydantic
Requires-Dist: sentence-transformers
Requires-Dist: stanza
Requires-Dist: cohere
Requires-Dist: numpy
Provides-Extra: test
Requires-Dist: pytest>=8.2.2; extra == "test"
Requires-Dist: pytest-cov; extra == "test"
